nbrw/NBRW.py
nbrw/__init__.py
nbrw/extra_graphs.py
nbrw-0.1.5.dist-info/METADATA
nbrw-0.1.5.dist-info/WHEEL
nbrw-0.1.5.dist-info/licenses/LICENSE
nbrw-0.1.5.dist-info/RECORD
