Metadata-Version: 2.3
Name: NBRW
Version: 0.1.5
Summary: A module for modeling non-backtracking random walks on graphs and computing kemeny's constant.
Project-URL: Homepage, https://github.com/mwshumway/NBRW
Project-URL: Issues, https://github.com/mwshumway/NBRW/issues
Author-email: Matthew Shumway <mwshumway7@gmail.com>
Classifier: License :: OSI Approved :: MIT License
Classifier: Operating System :: OS Independent
Classifier: Programming Language :: Python :: 3
Requires-Python: >=3.8
